portlive/__init__.py
portlive/_portlive.py
portlive/exceptions.py
portlive-1.0.0.dist-info/LICENSE
portlive-1.0.0.dist-info/METADATA
portlive-1.0.0.dist-info/WHEEL
portlive-1.0.0.dist-info/top_level.txt
portlive-1.0.0.dist-info/RECORD
